janus/__init__.py
janus/experiment.py
janus/utils.py
janus/variant.py
janus_web_ab_testing-0.1.6.dist-info/LICENSE
janus_web_ab_testing-0.1.6.dist-info/METADATA
janus_web_ab_testing-0.1.6.dist-info/WHEEL
janus_web_ab_testing-0.1.6.dist-info/RECORD
