Metadata-Version: 2.1
Name: janus-web-ab-testing
Version: 0.1.6
Summary: Janus, an A/B Test Framework.
License: MIT
Author: Luan Fernandes
Author-email: luangabriel70@gmail.com
Requires-Python: >=3.11,<4.0
Classifier: License :: OSI Approved :: MIT License
Classifier: Programming Language :: Python :: 3
Classifier: Programming Language :: Python :: 3.11
Requires-Dist: bayesian-testing (>=0.7.0,<0.8.0)
Requires-Dist: pandas (>=2.2.2,<3.0.0)
Requires-Dist: tabulate (>=0.9.0,<0.10.0)
